Workbook

Sheet Calculateur
A1: CURSAUDIT — CALCULATEUR DE TARIFICATION
A2: Variables modifiables en jaune · Résultats calculés en vert
A4: PARAMÈTRES DU MANUSCRIT | D4: PARAMÈTRES COMMERCIAUX | G4: 2 | H4: 3 | I4: 4
A5: Nombre de pages | B5: 150 | C5: pages | D5: Multiplicateur de prix | E5: 4 | F5: × coût IA | G5: =+G7-G6 -> 117.69352 | H5: =+H7-H6 -> 235.38703 | I5: =+I7-I6 -> 353.08055
A6: Unités analysées par page | B6: 8.5 | C6: moyenne observée | D6: Marge de sécurité coût IA | E6: 15 | F6: % | G6: =+$E$16 -> 117.69352 | H6: =+$E$16 -> 117.69352 | I6: =+$E$16 -> 117.69352
A7: Nombre de dimensions analysées | B7: 30 | C7: de 6 à 30+ | D7: TVA | E7: 21 | F7: % | G7: =+G6*G4 -> 235.38703 | H7: =+H6*H4 -> 353.08055 | I7: =+I6*I4 -> 470.77406
A8: Mode IA | B8: 2 IA | C8: liste déroulante | D8: Remise éventuelle | E8: 0 | F8: %
A9: Type de rapport | B9: Rapport complet | C9: liste déroulante
A11: HYPOTHÈSES DE COÛT — MODIFIABLES | D11: RÉSULTATS
A12: Coût de base par unité pour 8 dimensions | B12: 0.013 | C12: € / unité | D12: Unités totales estimées | E12: =B5*B6 -> 1275
A13: Dimensions de référence | B13: 8 | C13: dimensions | D13: Facteur dimensions | E13: =B7/B13 -> 3.75
A14: Facteur mode IA | B14: =IF(B8="1 IA",1,IF(B8="2 IA",1.55,IF(B8="2 IA + confrontation ciblée",1.9,IF(B8="2 IA + arbitrage dialogique",2.35,1)))) -> 1.55 | D14: Coût brut analyse IA | E14: =E12*B12*E13*B14 -> 96.342188 | F14: €
A15: Coût rapport | B15: =IF(B9="Aucun",0,IF(B9="Synthèse courte",2,IF(B9="Rapport complet",6,0))) -> 6 | D15: Coût IA + rapport | E15: =E14+B15 -> 102.34219 | F15: €
D16: Coût avec sécurité | E16: =E15*(1+E6/100) -> 117.69352 | F16: €
D17: Prix public HT | E17: =E16*E5*(1-E8/100) -> 470.77406 | F17: €
D18: TVA | E18: =E17*E7/100 -> 98.862553 | F18: €
D19: Prix public TTC | E19: =E17+E18 -> 569.63662 | F19: €
D20: Marge bénéficiaire brute | E20: =+E19-E16*E7/100-E16 -> 427.22746
A21: Lecture de la formule
A22: Coût analyse = pages × unités/page × coût/unité × (dimensions / dimensions de référence) × facteur du mode IA.
A23: Prix HT = (coût analyse + coût rapport) × sécurité × multiplicateur × (1 - remise).

Sheet Modes & hypothèses
A1: Mode IA | B1: Facteur proposé | C1: Description | D1: Quand l’utiliser
A2: 1 IA | B2: 1 | C2: Une IA analyse toutes les lignes. | D2: Entrée de gamme / scan exhaustif.
A3: 2 IA | B3: 1.55 | C3: Deuxième IA relit et contrôle la première. | D3: Réduction des angles morts.
A4: 2 IA + confrontation ciblée | B4: 1.9 | C4: La seconde IA conteste seulement les points sensibles ou désaccords. | D4: Bon compromis coût / profondeur.
A5: 2 IA + arbitrage dialogique | B5: 2.35 | C5: Deux IA argumentent les désaccords puis consolidation/arbitrage. | D5: Niveau expert maximal.
A7: Type de rapport | B7: Coût IA indicatif | C7: Description | D7: Hypothèse modifiable dans Calculateur
A8: Aucun | B8: 0 | C8: Excel / résultats structurés uniquement. | D8: 0 €
A9: Synthèse courte | B9: 2 | C9: Rapport synthétique d’environ 8–15 pages. | D9: 2 €
A10: Rapport complet | B10: 6 | C10: Rapport rédigé, motifs, recommandations, traçabilité. | D10: 6 €
A12: Hypothèse de calibration | B12: Valeur | C12: Commentaire
A13: Coût/unité pour 8 dimensions | B13: 0.013 | C13: Calibré pour donner ~16,6 € sur 150 pages, 8 dimensions, 1 IA, 8,5 unités/page.
A14: Unités/page | B14: 8.5 | C14: Moyenne issue de l’expérimentation actuelle ; à ajuster selon densité du manuscrit.
A15: Dimensions de référence | B15: 8 | C15: Le coût varie proportionnellement au nombre de dimensions analysées.

Sheet Scénarios
A1: Pages | B1: Dimensions | C1: Mode IA | D1: Rapport | E1: Multiplicateur | F1: Coût brut analyse | G1: Coût + rapport | H1: Coût sécurisé | I1: Prix HT | J1: TVA | K1: Prix TTC
A2: 50 | B2: 8 | C2: 1 IA | D2: Synthèse courte | E2: 3 | F2: =A2*Calculateur!$B$6*Calculateur!$B$12*(B2/Calculateur!$B$13)*IF(C2="1 IA",1,IF(C2="2 IA",1.55,IF(C2="2 IA + confrontation ciblée",1.9,2.35))) -> 5.525 | G2: =F2+IF(D2="Aucun",0,IF(D2="Synthèse courte",2,6)) -> 7.525 | H2: =G2*(1+Calculateur!$E$6/100) -> 8.65375 | I2: =H2*E2*(1-Calculateur!$E$8/100) -> 25.96125 | J2: =I2*Calculateur!$E$7/100 -> 5.4518625 | K2: =I2+J2 -> 31.413112
A3: 100 | B3: 8 | C3: 1 IA | D3: Synthèse courte | E3: 3 | F3: =A3*Calculateur!$B$6*Calculateur!$B$12*(B3/Calculateur!$B$13)*IF(C3="1 IA",1,IF(C3="2 IA",1.55,IF(C3="2 IA + confrontation ciblée",1.9,2.35))) -> 11.05 | G3: =F3+IF(D3="Aucun",0,IF(D3="Synthèse courte",2,6)) -> 13.05 | H3: =G3*(1+Calculateur!$E$6/100) -> 15.0075 | I3: =H3*E3*(1-Calculateur!$E$8/100) -> 45.0225 | J3: =I3*Calculateur!$E$7/100 -> 9.454725 | K3: =I3+J3 -> 54.477225
A4: 150 | B4: 8 | C4: 1 IA | D4: Synthèse courte | E4: 3 | F4: =A4*Calculateur!$B$6*Calculateur!$B$12*(B4/Calculateur!$B$13)*IF(C4="1 IA",1,IF(C4="2 IA",1.55,IF(C4="2 IA + confrontation ciblée",1.9,2.35))) -> 16.575 | G4: =F4+IF(D4="Aucun",0,IF(D4="Synthèse courte",2,6)) -> 18.575 | H4: =G4*(1+Calculateur!$E$6/100) -> 21.36125 | I4: =H4*E4*(1-Calculateur!$E$8/100) -> 64.08375 | J4: =I4*Calculateur!$E$7/100 -> 13.457587 | K4: =I4+J4 -> 77.541337
A5: 250 | B5: 8 | C5: 1 IA | D5: Synthèse courte | E5: 3 | F5: =A5*Calculateur!$B$6*Calculateur!$B$12*(B5/Calculateur!$B$13)*IF(C5="1 IA",1,IF(C5="2 IA",1.55,IF(C5="2 IA + confrontation ciblée",1.9,2.35))) -> 27.625 | G5: =F5+IF(D5="Aucun",0,IF(D5="Synthèse courte",2,6)) -> 29.625 | H5: =G5*(1+Calculateur!$E$6/100) -> 34.06875 | I5: =H5*E5*(1-Calculateur!$E$8/100) -> 102.20625 | J5: =I5*Calculateur!$E$7/100 -> 21.463312 | K5: =I5+J5 -> 123.66956
A6: 150 | B6: 15 | C6: 1 IA | D6: Rapport complet | E6: 4 | F6: =A6*Calculateur!$B$6*Calculateur!$B$12*(B6/Calculateur!$B$13)*IF(C6="1 IA",1,IF(C6="2 IA",1.55,IF(C6="2 IA + confrontation ciblée",1.9,2.35))) -> 31.078125 | G6: =F6+IF(D6="Aucun",0,IF(D6="Synthèse courte",2,6)) -> 37.078125 | H6: =G6*(1+Calculateur!$E$6/100) -> 42.639844 | I6: =H6*E6*(1-Calculateur!$E$8/100) -> 170.55937 | J6: =I6*Calculateur!$E$7/100 -> 35.817469 | K6: =I6+J6 -> 206.37684
A7: 150 | B7: 30 | C7: 1 IA | D7: Rapport complet | E7: 4 | F7: =A7*Calculateur!$B$6*Calculateur!$B$12*(B7/Calculateur!$B$13)*IF(C7="1 IA",1,IF(C7="2 IA",1.55,IF(C7="2 IA + confrontation ciblée",1.9,2.35))) -> 62.15625 | G7: =F7+IF(D7="Aucun",0,IF(D7="Synthèse courte",2,6)) -> 68.15625 | H7: =G7*(1+Calculateur!$E$6/100) -> 78.379687 | I7: =H7*E7*(1-Calculateur!$E$8/100) -> 313.51875 | J7: =I7*Calculateur!$E$7/100 -> 65.838937 | K7: =I7+J7 -> 379.35769
A8: 150 | B8: 30 | C8: 2 IA | D8: Rapport complet | E8: 4 | F8: =A8*Calculateur!$B$6*Calculateur!$B$12*(B8/Calculateur!$B$13)*IF(C8="1 IA",1,IF(C8="2 IA",1.55,IF(C8="2 IA + confrontation ciblée",1.9,2.35))) -> 96.342188 | G8: =F8+IF(D8="Aucun",0,IF(D8="Synthèse courte",2,6)) -> 102.34219 | H8: =G8*(1+Calculateur!$E$6/100) -> 117.69352 | I8: =H8*E8*(1-Calculateur!$E$8/100) -> 470.77406 | J8: =I8*Calculateur!$E$7/100 -> 98.862553 | K8: =I8+J8 -> 569.63662
A9: 150 | B9: 30 | C9: 2 IA + confrontation ciblée | D9: Rapport complet | E9: 4 | F9: =A9*Calculateur!$B$6*Calculateur!$B$12*(B9/Calculateur!$B$13)*IF(C9="1 IA",1,IF(C9="2 IA",1.55,IF(C9="2 IA + confrontation ciblée",1.9,2.35))) -> 118.09687 | G9: =F9+IF(D9="Aucun",0,IF(D9="Synthèse courte",2,6)) -> 124.09687 | H9: =G9*(1+Calculateur!$E$6/100) -> 142.71141 | I9: =H9*E9*(1-Calculateur!$E$8/100) -> 570.84562 | J9: =I9*Calculateur!$E$7/100 -> 119.87758 | K9: =I9+J9 -> 690.72321
A10: 150 | B10: 30 | C10: 2 IA + arbitrage dialogique | D10: Rapport complet | E10: 4 | F10: =A10*Calculateur!$B$6*Calculateur!$B$12*(B10/Calculateur!$B$13)*IF(C10="1 IA",1,IF(C10="2 IA",1.55,IF(C10="2 IA + confrontation ciblée",1.9,2.35))) -> 146.06719 | G10: =F10+IF(D10="Aucun",0,IF(D10="Synthèse courte",2,6)) -> 152.06719 | H10: =G10*(1+Calculateur!$E$6/100) -> 174.87727 | I10: =H10*E10*(1-Calculateur!$E$8/100) -> 699.50906 | J10: =I10*Calculateur!$E$7/100 -> 146.8969 | K10: =I10+J10 -> 846.40597
A11: 250 | B11: 30 | C11: 2 IA + arbitrage dialogique | D11: Rapport complet | E11: 5 | F11: =A11*Calculateur!$B$6*Calculateur!$B$12*(B11/Calculateur!$B$13)*IF(C11="1 IA",1,IF(C11="2 IA",1.55,IF(C11="2 IA + confrontation ciblée",1.9,2.35))) -> 243.44531 | G11: =F11+IF(D11="Aucun",0,IF(D11="Synthèse courte",2,6)) -> 249.44531 | H11: =G11*(1+Calculateur!$E$6/100) -> 286.86211 | I11: =H11*E11*(1-Calculateur!$E$8/100) -> 1434.3105 | J11: =I11*Calculateur!$E$7/100 -> 301.20521 | K11: =I11+J11 -> 1735.5158

Sheet Grille dimensions
A1: Niveau | B1: Nombre de dimensions | C1: Exemples de dimensions couvertes | D1: Positionnement
A2: Essentiel | B2: 8 | C2: Type d’énoncé; statut épistémique; besoin de preuve; biais/influence; référence; alerte; motif; diagnostic bref. | D2: Lecture exhaustive, coût minimal.
A3: Approfondi | B3: 15 | C3: Ajoute fonctions narrative/pédagogique/argumentative, robustesse, validation, procédés, recommandation. | D3: Analyse plus éditoriale.
A4: Expert | B4: 30 | C4: Grille complète : indépendance de validation, audit aveugle, relation institutionnelle, résonances, diagnostic détaillé, etc. | D4: Profondeur maximale.
A5: Libre | B5: -34 | C5: L’utilisateur choisit directement le nombre de dimensions dans le Calculateur. | D5: Permet une tarification continue.
